LICENSE
MANIFEST.in
README.md
TODO
alsaaudio.c
alsaaudio.pyi
isine.py
loopback.py
mixertest.py
play_rusage.py
playbacktest.py
playwav.py
recordtest.py
setup.py
test.py
doc/Makefile
doc/conf.py
doc/index.rst
doc/libalsaaudio.rst
doc/pyalsaaudio.rst
doc/terminology.rst
doc/gh-pages/genindex.html
doc/gh-pages/index.html
doc/gh-pages/libalsaaudio.html
doc/gh-pages/py-modindex.html
doc/gh-pages/pyalsaaudio.html
doc/gh-pages/search.html
doc/gh-pages/searchindex.js
doc/gh-pages/terminology.html
doc/gh-pages/_static/ajax-loader.gif
doc/gh-pages/_static/alabaster.css
doc/gh-pages/_static/basic.css
doc/gh-pages/_static/comment-bright.png
doc/gh-pages/_static/comment-close.png
doc/gh-pages/_static/comment.png
doc/gh-pages/_static/custom.css
doc/gh-pages/_static/default.css
doc/gh-pages/_static/doctools.js
doc/gh-pages/_static/documentation_options.js
doc/gh-pages/_static/down-pressed.png
doc/gh-pages/_static/down.png
doc/gh-pages/_static/file.png
doc/gh-pages/_static/forkme_right_darkblue_121621.png
doc/gh-pages/_static/graphviz.css
doc/gh-pages/_static/jquery-3.1.0.js
doc/gh-pages/_static/jquery.js
doc/gh-pages/_static/language_data.js
doc/gh-pages/_static/minus.png
doc/gh-pages/_static/plus.png
doc/gh-pages/_static/pygments.css
doc/gh-pages/_static/searchtools.js
doc/gh-pages/_static/sidebar.js
doc/gh-pages/_static/sphinx_highlight.js
doc/gh-pages/_static/underscore-1.3.1.js
doc/gh-pages/_static/underscore.js
doc/gh-pages/_static/up-pressed.png
doc/gh-pages/_static/up.png
doc/gh-pages/_static/websupport.js
doc/gh-pages/autoapi/index.html
doc/gh-pages/autoapi/alsaaudio/index.html
doc/gh-pages/autoapi/conf/index.html
doc/gh-pages/autoapi/isine/index.html
doc/gh-pages/autoapi/loopback/index.html
doc/gh-pages/autoapi/mixertest/index.html
doc/gh-pages/autoapi/play_rusage/index.html
doc/gh-pages/autoapi/playbacktest/index.html
doc/gh-pages/autoapi/playwav/index.html
doc/gh-pages/autoapi/recordtest/index.html
doc/gh-pages/autoapi/setup/index.html
pyalsaaudio.egg-info/PKG-INFO
pyalsaaudio.egg-info/SOURCES.txt
pyalsaaudio.egg-info/dependency_links.txt
pyalsaaudio.egg-info/top_level.txt