Metadata-Version: 2.1
Name: pyalsaaudio
Version: 0.11.0
Summary: ALSA bindings
Home-page: http://larsimmisch.github.io/pyalsaaudio/
Author: Casper Wilstrup
Author-email: cwi@aves.dk
Maintainer: Lars Immisch
Maintainer-email: lars@ibp.de
License: PSF
Platform: posix
Classifier: Development Status :: 4 - Beta
Classifier: Intended Audience :: Developers
Classifier: License :: OSI Approved :: Python Software Foundation License
Classifier: Operating System :: POSIX :: Linux
Classifier: Programming Language :: Python :: 2
Classifier: Programming Language :: Python :: 3
Classifier: Topic :: Multimedia :: Sound/Audio
Classifier: Topic :: Multimedia :: Sound/Audio :: Mixers
Classifier: Topic :: Multimedia :: Sound/Audio :: Players
Classifier: Topic :: Multimedia :: Sound/Audio :: Capture/Recording
License-File: LICENSE
